bytedance_gs_wms_sim/__init__.py
bytedance_gs_wms_sim-0.0.1.dist-info/METADATA
bytedance_gs_wms_sim-0.0.1.dist-info/WHEEL
bytedance_gs_wms_sim-0.0.1.dist-info/top_level.txt
bytedance_gs_wms_sim-0.0.1.dist-info/RECORD
