Metadata-Version: 2.1
Name: bytedance-gs-wms-sim
Version: 0.0.1
Summary: A simple package named bytedance_gs_wms_sim
Home-page: https://github.com/artifact/bytedance_gs_wms_sim.git
Author: artifact
Author-email: artifact@example.com
License: UNKNOWN
Platform: UNKNOWN
Classifier: Programming Language :: Python :: 3
Classifier: License :: OSI Approved :: MIT License
Classifier: Operating System :: OS Independent
